{
    "CallerReference": "vkp-consulting-fr-2025-09-23-01",
    "Comment": "VKP Consulting static site via S3 + CloudFront (OAC)",
    "Enabled": true,
    "IsIPV6Enabled": true,
    "Aliases": {
      "Quantity": 2,
      "Items": [
        "vkp-consulting.fr",
        "www.vkp-consulting.fr"
      ]
    },
    "Origins": {
      "Quantity": 1,
      "Items": [
        {
          "Id": "s3-origin-vkp",
          "DomainName": "vkp-consulting.fr.s3.eu-north-1.amazonaws.com",
          "S3OriginConfig": {
            "OriginAccessIdentity": ""
          },
          "OriginAccessControlId": "E3QY4UMB9YVA18"
        }
      ]
    },
    "DefaultRootObject": "index.html",
    "DefaultCacheBehavior": {
      "TargetOriginId": "s3-origin-vkp",
      "ViewerProtocolPolicy": "redirect-to-https",
      "AllowedMethods": {
        "Quantity": 2,
        "Items": ["GET", "HEAD"],
        "CachedMethods": {
          "Quantity": 2,
          "Items": ["GET", "HEAD"]
        }
      },
      "Compress": true,
      "CachePolicyId": "658327ea-f89d-4fab-a63d-7e88639e58f6" 
    },
    "CustomErrorResponses": {
      "Quantity": 0
    },
    "PriceClass": "PriceClass_100",
    "Restrictions": {
      "GeoRestriction": {
        "RestrictionType": "none",
        "Quantity": 0
      }
    },
    "ViewerCertificate": {
      "ACMCertificateArn": "arn:aws:acm:us-east-1:088455116440:certificate/e3774345-7028-415a-ab57-bd1f8e02a021",
      "SSLSupportMethod": "sni-only",
      "MinimumProtocolVersion": "TLSv1.2_2021",
      "Certificate": "arn:aws:acm:us-east-1:088455116440:certificate/e3774345-7028-415a-ab57-bd1f8e02a021",
      "CertificateSource": "acm"
    },
    "HttpVersion": "http2"
  }
  